click-stubs/METADATA.toml
click-stubs/__init__.pyi
click-stubs/_termui_impl.pyi
click-stubs/core.pyi
click-stubs/decorators.pyi
click-stubs/exceptions.pyi
click-stubs/formatting.pyi
click-stubs/globals.pyi
click-stubs/parser.pyi
click-stubs/termui.pyi
click-stubs/testing.pyi
click-stubs/types.pyi
click-stubs/utils.pyi
types_click-7.1.7.dist-info/METADATA
types_click-7.1.7.dist-info/WHEEL
types_click-7.1.7.dist-info/top_level.txt
types_click-7.1.7.dist-info/RECORD
