Metadata-Version: 2.1
Name: types-click
Version: 7.1.7
Summary: Typing stubs for click
Home-page: https://github.com/python/typeshed
License: Apache-2.0 license
Platform: UNKNOWN
Classifier: License :: OSI Approved :: Apache Software License
Classifier: Typing :: Typed
